autoview/__init__.py
autoview/explore.py
autoview/report.py
autoview/visualize.py
autoview-0.1.0.dist-info/METADATA
autoview-0.1.0.dist-info/WHEEL
autoview-0.1.0.dist-info/top_level.txt
autoview-0.1.0.dist-info/RECORD
