Metadata-Version: 2.4
Name: autoview
Version: 0.1.0
Summary: One-line Python EDA assistant: auto-summary, insights, and visual report generation
Home-page: https://github.com/avinash-betha/autoview
Author: Avinash Betha
Author-email: avinashb1581@gmail.com
License: MIT
Project-URL: Documentation, https://github.com/avinash-betha/autoview
Project-URL: Source, https://github.com/avinash-betha/autoview
Project-URL: Tracker, https://github.com/avinash-betha/autoview/issues
Classifier: Development Status :: 3 - Alpha
Classifier: Intended Audience :: Developers
Classifier: Intended Audience :: Science/Research
Classifier: License :: OSI Approved :: MIT License
Classifier: Programming Language :: Python :: 3
Classifier: Programming Language :: Python :: 3.6
Classifier: Programming Language :: Python :: 3.7
Classifier: Programming Language :: Python :: 3.8
Classifier: Programming Language :: Python :: 3.9
Classifier: Programming Language :: Python :: 3.10
Classifier: Topic :: Scientific/Engineering :: Information Analysis
Classifier: Topic :: Utilities
Requires-Python: >=3.6
Requires-Dist: pandas>=1.0
Requires-Dist: seaborn>=0.11
Requires-Dist: matplotlib>=3.3
Requires-Dist: tabulate>=0.8
Requires-Dist: missingno>=0.5
Requires-Dist: scikit-learn>=0.24
Dynamic: author
Dynamic: author-email
Dynamic: classifier
Dynamic: description
Dynamic: description-content-type
Dynamic: home-page
Dynamic: license
Dynamic: project-url
Dynamic: requires-dist
Dynamic: requires-python
Dynamic: summary
